pytrackeres/__init__.py
pytrackeres/main.py
pytrackeres/url_generator/__init__.py
pytrackeres/url_generator/afiliacion.py
pytrackeres/url_generator/bing_ads.py
pytrackeres/url_generator/colaboracion.py
pytrackeres/url_generator/comparador.py
pytrackeres/url_generator/core.py
pytrackeres/url_generator/display.py
pytrackeres/url_generator/emailing.py
pytrackeres/url_generator/google_ads.py
pytrackeres/url_generator/social.py
pytrackeres-1.0.4.dist-info/METADATA
pytrackeres-1.0.4.dist-info/WHEEL
pytrackeres-1.0.4.dist-info/entry_points.txt
pytrackeres-1.0.4.dist-info/top_level.txt
pytrackeres-1.0.4.dist-info/RECORD
