Metadata-Version: 2.1
Name: pytrackeres
Version: 1.0.4
Summary: Herramienta para la generación de URLs de tracking en Eulerian.
Home-page: https://github.com/abutrag/pytrackeres
Author: abutrag
Author-email: a.butragueno@eulerian.com
Classifier: Programming Language :: Python :: 3
Classifier: License :: OSI Approved :: MIT License
Classifier: Operating System :: OS Independent
Requires-Python: >=3.7
